{
  "QA":[
    "QA Engineer",
    "Software Tester",
    "Test Engineer",
    "Quality Assurance Analyst",
    "Test Automation Engineer",
    "Manual Tester",
    "QA Tester",
    "QA Analyst",
    "Test Lead",
    "Quality Control Specialist",
    "Test Manager",
    "Test Coordinator",
    "Test Architect",
    "Test Consultant",
    "Quality Assurance Manager",
    "QA Automation Engineer",
    "Quality Assurance Tester",
    "SDET",
    "Testing Specialist",
    "Test Technician",
    "Менеджер технічної підтримки",
    "Performance Testing Engineer",
    "Quality Engineer ",
    "Інженер технічної підтримки",
    "Quality Customer Experience Manager",
    "Microsoft 365 Help Desk",
    "Technical Support Manager",
    "QA"
  ],
  "SEO":[
    "SEO Specialist",
    "SEO Manager",
    "SEO Analyst",
    "SEO Consultant",
    "SEO Strategist",
    "SEO Content Writer",
    "Digital Marketing Analyst",
    "SEM Specialist (Search Engine Marketing)",
    "Organic Search Specialist",
    "SEO Coordinator",
    "Link Building Specialist",
    "On-Page SEO Expert",
    "Off-Page SEO Specialist",
    "SEO Copywriter",
    "SEO Executive",
    "SEO Technician",
    "SEO Auditor",
    "SEO Content Manager",
    "SEO Campaign Manager",
    "SEO Data Analyst",
    "Google Analytics",
    "Content Marketing",
    "Backlink Analysis",
    "SEO Auditing",
    "Local SEO",
    "E-commerce SEO",
    "Media Buyer",
    "Таргет",
    "target",
    "Маркетолог",
    "SEO",
    "Спеціаліст з маркетингу та реклами",
    "Google Ads",
    "Traffic",
    "Веб-аналитик",
    "Аналитик данных веб-сайта",
    "Специалист по анализу веб-трафика",
    "Аналитик интернет-маркетинга",
    "Специалист по аналитике веб-сайтов",
    "Менеджер веб-аналитики",
    "Аналитик цифрового маркетинга",
    "Специалист по метрикам веб-сайта",
    "Аналитик веб-данных",
    "Аналитик пользовательского поведения",
    "Веб-аналитик e-commerce",
    "Специалист по конверсионной аналитике",
    "Аналитик веб-трафика",
    "Специалист по Google Analytics",
    "Аналитик Adobe Analytics",
    "Аналитик Yandex.Metrica",
    "Аналитик Яндекс.Метрика",
    "Аналитик веб-поведения пользователей",
    "Аналитик маркетинговых метрик",
    "Специалист по анализу медиа-показателей",
    "Web Analyst",
    "Web Analytics Specialist",
    "Digital Analyst",
    "Website Data Analyst",
    "Digital Marketing Analyst",
    "Online Analytics Manager",
    "Data Analytics Consultant",
    "E-commerce Analyst",
    "Google Analytics Specialist",
    "Web Traffic Analyst",
    "Conversion Rate Analyst",
    "Digital Insights Analyst",
    "Marketing Performance Analyst",
    "Digital Reporting Analyst",
    "User Behavior Analyst",
    "Data Analytics Manager",
    "Web Data Scientist",
    "SEO Analytics Specialist",
    "Web Measurement Analyst",
    "Customer Insights Analyst"
  ],
  "Content_Manager":[
    "Content Manager",
    "Content Coordinator",
    "Content Specialist",
    "Content Strategist",
    "Content Editor",
    "Content Writer",
    "Digital Content Manager",
    "Social Media Content Manager",
    "Web Content Manager",
    "SEO Content Manager",
    "Content Marketing Manager",
    "Blog Manager",
    "Editorial Manager",
    "Content Creation Manager",
    "Content Development Manager",
    "Content Production Manager",
    "Content Planner",
    "Content Curator",
    "Content Administrator",
    "Multimedia Content Manager",
    "КОНТЕНТ",
    "Social Media Content Manager",
    "E-commerce Content Manager",
    "Technical Content Manager",
    "Video Content Manager",
    "Content Management System (CMS)",
    "Content Strategy",
    "Content Marketing",
    "Copywriting",
    "Content Video Editor",
    "Social Media Video Editor"
  ],
  "Link_Builder":[
    "Link Builder",
    "Link Building Specialist",
    "Backlink Specialist",
    "SEO Link Builder",
    "Outreach Specialist",
    "Digital PR Specialist",
    "Off-Page SEO Specialist",
    "Link Acquisition Specialist",
    "Content Outreach Specialist",
    "Guest Posting Specialist",
    "Link Earning Specialist",
    "Link Development Manager",
    "Outreach Coordinator",
    "Link Building Consultant",
    "SEO Outreach Manager",
    "Inbound Link Builder",
    "Link Building Campaign Manager",
    "Backlink Outreach Specialist",
    "Link Strategy Manager",
    "Link Outreach Coordinator",
    "PR",
    "Employer Branding"
  ],
  "SMM":[
    "SMM менеджер",
    "Специалист по социальным медиа",
    "Менеджер по работе в социальных сетях",
    "Специалист по маркетингу",
    "SMM аналитик",
    "Контент менеджер в социальных сетях",
    "SMM координатор",
    "Специалист по продвижению в социальных медиа",
    "SMM консультант",
    "Специалист по рекламе в социальных сетях",
    "SMM специалист",
    "Менеджер по созданию контента",
    "SMM планировщик",
    "Специалист по взаимодействию с аудиторией",
    "SMM дизайнер",
    "SMM копирайтер",
    "Менеджер по взаимодействию с сообществом",
    "Специалист по медиапланированию в социальных медиа",
    "SMM аналитика",
    "SMM manager",
    "Account manager",
    "Акаунт менеджер",
    "Digital Маркетолог",
    "SMM"
  ],
  "Web_Developer":[
    "Веб программист",
    "Веб разработчик",
    "Разработчик веб-приложений",
    "Разработчик веб-приложений",
    "Front-end специалист",
    "Back-end специалист",
    "Full-stack специалист",
    "Веб-дизайнер и разработчик",
    "Веб-инженер",
    "Веб-программист HTML/CSS",
    "Разработчик пользовательских интерфейсов",
    "JavaScript разработчик",
    "PHP разработчик",
    "Python разработчик",
    "Ruby on Rails разработчик",
    "Web Programmer",
    "Web Developer",
    "Web Application Developer",
    "Web Designer and Developer",
    "Web Engineer",
    "HTML/CSS Web Programmer",
    "User Interface Developer",
    "PHP Developer",
    "Python Developer",
    "Ruby on Rails Developer",
    "Python Developer",
    "Ruby on Rails Developer",
    "UI developer",
    "Rive Animation",
    "WordPress",
    "shopify",
    "HTML",
    "Верстальник"
  ],
  "Project_Manager": [
    "Менеджер проекта",
    "Руководитель проекта",
    "Менеджер проектов",
    "Главный менеджер проектов",
    "Директор проектов",
    "Проджект-координатор",
    "Руководитель проектной группы",
    "Менеджер по управлению проектами",
    "Главный проектный менеджер",
    "Руководитель проектной команды",
    "Менеджер стратегических проектов",
    "Проектный лидер",
    "Проджект-аналитик",
    "Проджект-специалист",
    "Проджект-руководитель",
    "Технический менеджер проекта",
    "Менеджер операционных проектов",
    "Менеджер программы",
    "Управляющий проектами",
    "Project Manager",
    "Project Management",
    "Program Manager",
    "Project Lead",
    "Project Coordinator",
    "Project Director",
    "Senior Project Manager",
    "Project Team Leader",
    "Project Management Specialist",
    "Project Leader",
    "Program Director",
    "Project Analyst",
    "Technical Project Manager",
    "Operations Project Manager",
    "PM",
    "Project Manager"
  ],
  "Frontend": [
    "Front-end Developer",
    "Front-end Engineer",
    "JavaScript Developer",
    "UI Developer",
    "User Interface Developer",
    "Front-end Designer",
    "Web UI Developer",
    "Front-end Software Engineer",
    "Front-end Programmer",
    "JavaScript Engineer",
    "Front-end Web Designer",
    "Web Interface Developer",
    "Front-end Web Developer",
    "Front-end UX Developer",
    "Front-end Design Specialist",
    "Front-end Development Specialist",
    "Angular",
    "React",
    "Vue",
    "Frontend",
    "Front end",
    "Front-end"
  ],
  "Backend": [
    "Back-end Developer",
    "Back-end Engineer",
    "Server-side Developer",
    "Backend Software Developer",
    "Database Developer",
    "Back-end Programmer",
    "Server Developer",
    "Back-end Architect",
    "Backend Software Engineer",
    "Back-end Web Developer",
    "Back-end Development Specialist",
    "Backend Application Developer",
    "Backend Systems Developer",
    "Database Architect",
    "Server-side Engineer",
    "Server-side Programmer",
    "Back-end API Developer",
    "Backend Framework Developer",
    "Database Specialist",
    "Backend Coding Specialist",
    "Back end",
    "Backend",
    "Principal",
    "Software Engineer",
    "Scala",
    "Python",
    "GO",
    "GOLANG",
    "Back-end"
  ],
  "Database": [
    "Database Developer",
    "SQL Developer",
    "Database Engineer",
    "Database Programmer",
    "Database Software Developer",
    "Database Architect",
    "SQL Programmer",
    "Database Systems Developer",
    "Database Administrator",
    "Database Analyst",
    "Database Designer",
    "Database Specialist",
    "Data Engineer",
    "Database Management Developer",
    "ETL Developer (Extract, Transform, Load)",
    "NoSQL Developer",
    "Data Warehouse Developer",
    "Business Intelligence (BI) Developer",
    "Big Data Developer",
    "Database Design Specialist",
    "Big Data",
    "Siebel Developer",
    "DA",
    "Database",
    "DB",
    "DBA"
  ],
  "Systems_Analyst": [
    "Аналитик систем",
    "Бизнес-аналитик",
    "Аналитик процессов",
    "Аналитик бизнес-процессов",
    "Аналитик информационных систем",
    "Аналитик системной интеграции",
    "IT-аналитик",
    "Функциональный аналитик",
    "Аналитик требований",
    "Аналитик системной архитектуры",
    "Аналитик проектов",
    "Аналитик инфраструктуры",
    "Аналитик данных",
    "Интеграционный аналитик",
    "Аналитик автоматизации бизнес-процессов",
    "Аналитик ERP-систем",
    "Аналитик CRM-систем",
    "Аналитик управления данными",
    "Аналитик технических решений",
    "Systems Analyst",
    "Business Systems Analyst",
    "IT Analyst",
    "Process Analyst",
    "Business Process Analyst",
    "Information Systems Analyst",
    "Systems Integration Analyst",
    "Functional Analyst",
    "Requirements Analyst",
    "Systems Architecture Analyst",
    "Project Analyst",
    "Infrastructure Analyst",
    "Data Analyst",
    "Integration Analyst",
    "Business Process Automation Analyst",
    "ERP Systems Analyst",
    "CRM Systems Analyst",
    "Data Management Analyst",
    "Technical Solutions Analyst",
    "Technical Business Analyst",
    "Business Analyst",
    "Бізнес-аналітик",
    "Бізнес аналітик"
  ],
  "Game_Dev": [
    "Game Programmer",
    "Game Designer",
    "Game Artist",
    "Unity Developer",
    "Unreal Engine Developer",
    "Game Level Designer",
    "Game Tester",
    "Virtual Reality (VR) Developer",
    "Augmented Reality (AR) Developer",
    "Game Engine Developer",
    "Game Sound Designer",
    "Game Musician",
    "2D Game Developer",
    "3D Game Developer",
    "Mobile Game Developer",
    "Console Game Developer",
    "PC Game Developer",
    "Game Development Studio",
    "Game Monetization Specialist",
    "Game",
    "Unity"
  ],
  "Android": [
    "Мобильный разработчик Android",
    "Разработчик приложений для Android",
    "Разработчик мобильных приложений",
    "Android Software Engineer",
    "Android App Developer",
    "Java Developer for Android",
    "Android Application Developer",
    "Android Studio Developer",
    "Android UX/UI Designer",
    "Android Mobile Developer",
    "Android SDK Developer",
    "Android Kotlin Developer",
    "Android Game Developer",
    "Android Front-end Developer",
    "Android Back-end Developer",
    "Android UI/UX Developer",
    "Android App Programmer",
    "Android Mobile App Developer",
    "Android Test Engineer",
    "Android",
    "Kotlin"
  ],
  "iOS":[
    "Разработчик iOS",
    "iOS Application Developer",
    "Мобильный разработчик iOS",
    "iOS Software Engineer",
    "iOS App Developer",
    "Swift Developer",
    "Objective-C Developer",
    "Xcode Developer",
    "iOS User Interface (UI) Designer",
    "iOS Mobile Developer",
    "iOS SDK Developer",
    "iOS Kotlin Developer",
    "iOS Game Developer",
    "iOS Front-end Developer",
    "iOS Back-end Developer",
    "iOS UI/UX Developer",
    "iOS App Programmer",
    "iOS Test Engineer",
    "iOS App Store Optimization (ASO) Specialist",
    "Swift",
    "MacOS",
    "Ios"
  ],
  "UI_UX": [
    "User Interface Designer",
    "User Experience Designer",
    "Graphic Designer (UI/UX)",
    "Interface Designer",
    "Mobile Interface Designer",
    "Visual UI/UX Designer",
    "Interaction Designer",
    "Mobile App Designer",
    "Web Interface Designer",
    "Web App UI/UX Designer",
    "Social Media UI/UX Designer",
    "Game UI/UX Designer",
    "Adaptive UI/UX Designer",
    "User Experience Design Specialist",
    "Usability Designer",
    "Wireframe Designer",
    "Графический дизайнер интерфейса (UI)",
    "Дизайнер пользовательского опыта (UX)",
    "Интерфейсный дизайнер",
    "Дизайнер мобильных интерфейсов",
    "Визуальный дизайнер пользовательского интерфейса (UI)",
    "Дизайнер пользовательского взаимодействия",
    "Дизайнер мобильных приложений",
    "Дизайнер веб-интерфейсов",
    "Дизайнер интерфейсов веб-приложений",
    "Дизайнер пользовательского опыта веб-приложений",
    "Интерфейсный дизайнер для социальных сетей",
    "Дизайнер игровых интерфейсов",
    "Дизайнер медиа-приложений",
    "Дизайнер адаптивных интерфейсов",
    "UI",
    "UX",
    "UX-Writer"
  ],
  "Designer": [
    "Graphic designer",
    "Graphic design",
    "Web designer",
    "Web design",
    "Графический дизайнер",
    "Веб дизайнер",
    "Веб-дизайнер"
  ],
  "ERP": [
    "Специалист по ERP",
    "ERP Consultant",
    "Консультант по системам управления предприятием",
    "ERP Developer",
    "Разработчик ERP-систем",
    "ERP Implementation Specialist",
    "Специалист по внедрению ERP",
    "ERP Project Manager",
    "Менеджер проектов ERP",
    "ERP Analyst",
    "Аналитик ERP-систем",
    "ERP Support Specialist",
    "Специалист по поддержке ERP",
    "ERP Administrator",
    "Администратор ERP-системы",
    "ERP Business Analyst",
    "Бизнес-аналитик ERP",
    "ERP Functional Consultant",
    "Функциональный консультант ERP",
    "Business Development Manager"
  ],
  "Mobile":[
    "Swift",
    "Kotlin",
    "Android",
    "Flutter"
  ],
  "Customer_Service":[
    "Payments Systems Manager",
    "Customer Support Specialist",
    "Customer Support",
    "Customer Phone support",
    "Оператор служби підтримки"
  ],
  "Junior":[
    "junior",
    "Intern",
    "Trainee"
  ],
  "ServiceNow":[
    "ServiceNow"
  ],
  "Embedded":[
    "Embedded",
    "ESP 32",
    "arduino",
    "AOSP"
  ],
  "C": [
    "C"
  ],
  "HR": [
    "Рекрутер",
    "HRD",
    "HR",
    "Recruiter"
  ],
  "DevOps":[
    "Strategic Architect",
    "DevOps",
    "AWS",
    "GCP",
    "Google Cloud",
    "Digital Ocean",
    "Terraform",
    "Kubernetes",
    "Azure",
    "Architect",
    "Windows Ops Admin"
  ],
  "GO": [
    "Golang",
    "GO"
  ],
  "Sales": [
    "Affiliate manager",
    "PPC",
    "Спеціаліст з контекстної реклами",
    "Marketing Sourcer",
    "продажу в IT",
    "Affiliate",
    "Acquisition Manager ",
    "Sales Agent",
    "Key Affiliate Manager",
    "Client Relationship Manager",
    "Менеджер з продажу IT-послуг",
    "account manager",
    "B2B",
    "Sales",
    "SDR"
  ],
  "Office_manager":[
    "Аssіstant Product Owner",
    "Office manager"
  ],
  "DOT_NET": [
    ".NET",
    "C#"
  ],
  "Full_Stack":[
    "Full-Stack",
    "Full Stack",
    "FullStack"
  ],
  "Angular":[
    "Angular"
  ],
  "React":[
    "React"
  ],
  "Crypto":[
    "Cryptocurrency",
    "Blockchain",
    "Crypto"
  ],
  "Flutter":[
    "Flutter"
  ],
  "Java":[
    "Java"
  ],
  "Vue":[
    "Vue"
  ],
  "Lead":[
    "Lead"
  ],
  "SysAdmin":[
    "System Administrator",
    "Монтажник связи, интернета, линейщик",
    "Системний адміністратор",
    "Системный администратор"
  ],
  "JavaScript":[
    "TypeScript",
    "JavaScript",
    "JS",
    "TS",
    "MEAN"
  ],
  "Architect":[
    "Architect"
  ],
  "Senior":[
    "Senior"
  ],
  "Middle":[
    "Middle",
    "Mid"
  ],
  "PHP":[
    "Laravel",
    "PHP"
  ],
  "Scrum_Master":[
    "Scrum Master",
    "Scrum"
  ]
}